MLcps/GridSearchCV-object.pickle
MLcps/__init__.py
MLcps/getCPS.py
MLcps/metrices.csv
MLcps-0.0.6.dist-info/LICENSE.toml
MLcps-0.0.6.dist-info/METADATA
MLcps-0.0.6.dist-info/WHEEL
MLcps-0.0.6.dist-info/top_level.txt
MLcps-0.0.6.dist-info/RECORD
