Metadata-Version: 2.1
Name: MLcps
Version: 0.0.6
Summary: Calculate a Machine Learning (ML) performance metric called MLcps: ML Cumulative Performance Score.
Home-page: https://github.com/FunctionalUrology/MLcps
Author: Akshay
Author-email: akshaysuhag1996@gmail.com
Project-URL: Bug Tracker, https://github.com/FunctionalUrology/MLcps/issues
Classifier: Programming Language :: Python :: 3
Classifier: License :: OSI Approved :: MIT License
Classifier: Operating System :: OS Independent
Requires-Python: >=3.8
License-File: LICENSE.toml
Requires-Dist: rpy2
Requires-Dist: pandas
Requires-Dist: scikit-learn
Requires-Dist: imbalanced-learn
Requires-Dist: plotly
